{
    "key": "group_668c42428f29a",
    "title": "Upgrades",
    "fields": [
        {
            "key": "field_668c424278da9",
            "label": "Description",
            "name": "upgrade_description",
            "aria-label": "",
            "type": "text",
            "instructions": "",
            "required": 1,
            "conditional_logic": 0,
            "wrapper": {
                "width": "",
                "class": "",
                "id": ""
            },
            "default_value": "",
            "maxlength": "",
            "placeholder": "",
            "prepend": "",
            "append": ""
        },
        {
            "key": "field_668c448bd514d",
            "label": "Setup Fee",
            "name": "upgrades_setup_fee",
            "aria-label": "",
            "type": "number",
            "instructions": "",
            "required": 0,
            "conditional_logic": 0,
            "wrapper": {
                "width": "40",
                "class": "",
                "id": ""
            },
            "default_value": 0,
            "min": 0,
            "max": "",
            "placeholder": "",
            "step": "",
            "prepend": "£",
            "append": ""
        },
        {
            "key": "field_668c427378daa",
            "label": "Price",
            "name": "upgrades_price",
            "aria-label": "",
            "type": "number",
            "instructions": "",
            "required": 1,
            "conditional_logic": 0,
            "wrapper": {
                "width": "30",
                "class": "",
                "id": ""
            },
            "default_value": "",
            "min": 0,
            "max": "",
            "placeholder": "",
            "step": "",
            "prepend": "£",
            "append": ""
        },
        {
            "key": "field_668c470ae4a88",
            "label": "Price Type",
            "name": "upgrades_price_type",
            "aria-label": "",
            "type": "radio",
            "instructions": "",
            "required": 1,
            "conditional_logic": 0,
            "wrapper": {
                "width": "30",
                "class": "",
                "id": ""
            },
            "choices": {
                "set": "Set Fee",
                "pp": "Per Person"
            },
            "default_value": "set",
            "return_format": "value",
            "allow_null": 0,
            "other_choice": 0,
            "layout": "horizontal",
            "save_other_choice": 0
        },
        {
            "key": "field_668c443cd514c",
            "label": "Minimum Order",
            "name": "upgrades_minimum_order",
            "aria-label": "",
            "type": "number",
            "instructions": "",
            "required": 0,
            "conditional_logic": [
                [
                    {
                        "field": "field_668c470ae4a88",
                        "operator": "==",
                        "value": "pp"
                    }
                ]
            ],
            "wrapper": {
                "width": "30",
                "class": "",
                "id": ""
            },
            "default_value": 0,
            "min": 0,
            "max": "",
            "placeholder": "",
            "step": "",
            "prepend": "",
            "append": "people"
        },
        {
            "key": "field_668c4561d514f",
            "label": "Price for",
            "name": "upgrades_price_for",
            "aria-label": "",
            "type": "group",
            "instructions": "",
            "required": 0,
            "conditional_logic": [
                [
                    {
                        "field": "field_668c470ae4a88",
                        "operator": "==",
                        "value": "set"
                    }
                ]
            ],
            "wrapper": {
                "width": "70",
                "class": "",
                "id": ""
            },
            "layout": "table",
            "sub_fields": [
                {
                    "key": "field_668c4bea13b35",
                    "label": "Number",
                    "name": "upgrades_price_for_number",
                    "aria-label": "",
                    "type": "number",
                    "instructions": "eg. 100",
                    "required": 1,
                    "conditional_logic": 0,
                    "wrapper": {
                        "width": "50",
                        "class": "",
                        "id": ""
                    },
                    "default_value": "",
                    "min": 0,
                    "max": "",
                    "placeholder": "",
                    "step": 1,
                    "prepend": "",
                    "append": ""
                },
                {
                    "key": "field_668c4c2613b36",
                    "label": "Unit",
                    "name": "upgrades_price_for_unit",
                    "aria-label": "",
                    "type": "text",
                    "instructions": "eg. people",
                    "required": 1,
                    "conditional_logic": 0,
                    "wrapper": {
                        "width": "",
                        "class": "",
                        "id": ""
                    },
                    "default_value": "",
                    "maxlength": "",
                    "placeholder": "",
                    "prepend": "",
                    "append": ""
                }
            ]
        },
        {
            "key": "field_668c45b8d5150",
            "label": "Additional Unit Cost",
            "name": "upgrades_additional_unit_cost",
            "aria-label": "",
            "type": "group",
            "instructions": "eg. £3 per person",
            "required": 0,
            "conditional_logic": [
                [
                    {
                        "field": "field_668c470ae4a88",
                        "operator": "==",
                        "value": "set"
                    }
                ]
            ],
            "wrapper": {
                "width": "30",
                "class": "",
                "id": ""
            },
            "layout": "table",
            "sub_fields": [
                {
                    "key": "field_668c4d30d6d8d",
                    "label": "Cost",
                    "name": "upgrades_additional_unit_cost_value",
                    "aria-label": "",
                    "type": "number",
                    "instructions": "",
                    "required": 0,
                    "conditional_logic": 0,
                    "wrapper": {
                        "width": "",
                        "class": "",
                        "id": ""
                    },
                    "default_value": "",
                    "min": "",
                    "max": "",
                    "placeholder": "",
                    "step": "",
                    "prepend": "£",
                    "append": ""
                },
                {
                    "key": "field_668c4d4bd6d8e",
                    "label": "Per",
                    "name": "upgrades_additional_unit_cost_unit",
                    "aria-label": "",
                    "type": "text",
                    "instructions": "",
                    "required": 1,
                    "conditional_logic": [
                        [
                            {
                                "field": "field_668c4d30d6d8d",
                                "operator": "!=empty"
                            }
                        ]
                    ],
                    "wrapper": {
                        "width": "",
                        "class": "",
                        "id": ""
                    },
                    "default_value": "",
                    "maxlength": "",
                    "placeholder": "",
                    "prepend": "",
                    "append": ""
                }
            ]
        },
        {
            "key": "field_668c4eea3c448",
            "label": "Extra Info",
            "name": "upgrades_extra_info",
            "aria-label": "",
            "type": "group",
            "instructions": "Displayed under the Description",
            "required": 0,
            "conditional_logic": 0,
            "wrapper": {
                "width": "",
                "class": "",
                "id": ""
            },
            "layout": "table",
            "sub_fields": [
                {
                    "key": "field_668c4f22df829",
                    "label": "Title",
                    "name": "upgrades_extra_info_title",
                    "aria-label": "",
                    "type": "text",
                    "instructions": "",
                    "required": 0,
                    "conditional_logic": 0,
                    "wrapper": {
                        "width": "",
                        "class": "",
                        "id": ""
                    },
                    "default_value": "",
                    "maxlength": "",
                    "placeholder": "",
                    "prepend": "",
                    "append": ""
                },
                {
                    "key": "field_668c4f39df82a",
                    "label": "Info",
                    "name": "upgrades_extra_info_text",
                    "aria-label": "",
                    "type": "textarea",
                    "instructions": "",
                    "required": 0,
                    "conditional_logic": 0,
                    "wrapper": {
                        "width": "",
                        "class": "",
                        "id": ""
                    },
                    "default_value": "",
                    "maxlength": "",
                    "rows": "",
                    "placeholder": "",
                    "new_lines": ""
                }
            ]
        },
        {
            "key": "field_668c49c783d21",
            "label": "Image",
            "name": "upgrades_image",
            "aria-label": "",
            "type": "image",
            "instructions": "",
            "required": 0,
            "conditional_logic": 0,
            "wrapper": {
                "width": "",
                "class": "",
                "id": ""
            },
            "return_format": "url",
            "library": "all",
            "min_width": "",
            "min_height": "",
            "min_size": "",
            "max_width": "",
            "max_height": "",
            "max_size": "",
            "mime_types": "",
            "preview_size": "medium"
        }
    ],
    "location": [
        [
            {
                "param": "post_type",
                "operator": "==",
                "value": "upgrade"
            }
        ]
    ],
    "menu_order": 0,
    "position": "normal",
    "style": "default",
    "label_placement": "top",
    "instruction_placement": "label",
    "hide_on_screen": [
        "permalink",
        "the_content",
        "excerpt",
        "discussion",
        "comments",
        "revisions",
        "slug",
        "author",
        "format",
        "page_attributes",
        "featured_image",
        "categories",
        "tags",
        "send-trackbacks"
    ],
    "active": true,
    "description": "",
    "show_in_rest": 1,
    "modified": 1720471467
}
